[{"date":"Tue, 23 Feb 2021 04:56:50 GMT","sloc":32,"lloc":8,"functions":4,"deliveredBugs":0.099,"maintainability":84.681,"lintErrors":1,"difficulty":7.429},{"date":"Tue, 23 Feb 2021 04:58:02 GMT","sloc":32,"lloc":8,"functions":4,"deliveredBugs":0.099,"maintainability":84.681,"lintErrors":1,"difficulty":7.429},{"date":"Tue, 23 Feb 2021 18:07:11 GMT","sloc":32,"lloc":8,"functions":4,"deliveredBugs":0.099,"maintainability":84.681,"lintErrors":1,"difficulty":7.429},{"date":"Tue, 23 Feb 2021 18:33:13 GMT","sloc":32,"lloc":8,"functions":4,"deliveredBugs":0.099,"maintainability":84.681,"lintErrors":1,"difficulty":7.429},{"date":"Wed, 24 Feb 2021 22:25:07 GMT","sloc":32,"lloc":8,"functions":4,"deliveredBugs":0.099,"maintainability":84.681,"lintErrors":1,"difficulty":7.429}]