{"info":{"file":"src/inter/http/service/api-service.js","fileShort":"service/api-service.js","fileSafe":"service_api_service_js","link":"files/service_api_service_js/index.html"},"complexity":{"methodAggregate":{"cyclomatic":2,"cyclomaticDensity":13.333,"halstead":{"bugs":0.126,"difficulty":13,"effort":4894.746,"length":76,"time":271.93,"vocabulary":31,"volume":376.519,"operands":{"distinct":18,"total":36,"identifiers":["__stripped__"]},"operators":{"distinct":13,"total":40,"identifiers":["__stripped__"]}},"params":3,"sloc":{"logical":15,"physical":29}},"settings":{"commonjs":false,"forin":false,"logicalor":true,"switchcase":true,"trycatch":false,"newmi":true},"classes":[],"dependencies":[],"errors":[],"lineEnd":29,"lineStart":1,"maintainability":77.931,"methods":[{"cyclomatic":1,"cyclomaticDensity":20,"halstead":{"bugs":0.031,"difficulty":6.286,"effort":589.382,"length":24,"time":32.743,"vocabulary":15,"volume":93.765,"operands":{"distinct":7,"total":11,"identifiers":["__stripped__"]},"operators":{"distinct":8,"total":13,"identifiers":["__stripped__"]}},"params":1,"sloc":{"logical":5,"physical":19},"errors":[],"lineEnd":26,"lineStart":8,"name":"<anonymous>","complexity":{"cyclomatic":1,"sloc":{"logical":5,"physical":19},"halstead":{"bugs":0.031,"difficulty":6.286,"effort":589.382,"length":24,"time":32.743,"vocabulary":15,"volume":93.765,"operands":{"distinct":7,"total":11,"identifiers":["__stripped__"]},"operators":{"distinct":8,"total":13,"identifiers":["__stripped__"]}}},"line":8},{"cyclomatic":1,"cyclomaticDensity":100,"halstead":{"bugs":0.003,"difficulty":1.5,"effort":12,"length":4,"time":0.667,"vocabulary":4,"volume":8,"operands":{"distinct":1,"total":1,"identifiers":["__stripped__"]},"operators":{"distinct":3,"total":3,"identifiers":["__stripped__"]}},"params":0,"sloc":{"logical":1,"physical":9},"errors":[],"lineEnd":20,"lineStart":12,"name":"<anonymous>","complexity":{"cyclomatic":1,"sloc":{"logical":1,"physical":9},"halstead":{"bugs":0.003,"difficulty":1.5,"effort":12,"length":4,"time":0.667,"vocabulary":4,"volume":8,"operands":{"distinct":1,"total":1,"identifiers":["__stripped__"]},"operators":{"distinct":3,"total":3,"identifiers":["__stripped__"]}}},"line":12},{"cyclomatic":2,"cyclomaticDensity":50,"halstead":{"bugs":0.035,"difficulty":6.857,"effort":710.484,"length":28,"time":39.471,"vocabulary":13,"volume":103.612,"operands":{"distinct":7,"total":16,"identifiers":["__stripped__"]},"operators":{"distinct":6,"total":12,"identifiers":["__stripped__"]}},"params":2,"sloc":{"logical":4,"physical":7},"errors":[],"lineEnd":19,"lineStart":13,"name":"<anonymous>","complexity":{"cyclomatic":2,"sloc":{"logical":4,"physical":7},"halstead":{"bugs":0.035,"difficulty":6.857,"effort":710.484,"length":28,"time":39.471,"vocabulary":13,"volume":103.612,"operands":{"distinct":7,"total":16,"identifiers":["__stripped__"]},"operators":{"distinct":6,"total":12,"identifiers":["__stripped__"]}}},"line":13},{"cyclomatic":1,"cyclomaticDensity":50,"halstead":{"bugs":0.003,"difficulty":3,"effort":30,"length":5,"time":1.667,"vocabulary":4,"volume":10,"operands":{"distinct":1,"total":2,"identifiers":["__stripped__"]},"operators":{"distinct":3,"total":3,"identifiers":["__stripped__"]}},"params":0,"sloc":{"logical":2,"physical":5},"errors":[],"lineEnd":25,"lineStart":21,"name":"<anonymous>","complexity":{"cyclomatic":1,"sloc":{"logical":2,"physical":5},"halstead":{"bugs":0.003,"difficulty":3,"effort":30,"length":5,"time":1.667,"vocabulary":4,"volume":10,"operands":{"distinct":1,"total":2,"identifiers":["__stripped__"]},"operators":{"distinct":3,"total":3,"identifiers":["__stripped__"]}}},"line":21}],"methodAverage":{"cyclomatic":1.25,"cyclomaticDensity":55,"halstead":{"bugs":0.018,"difficulty":4.411,"effort":335.467,"length":15.25,"time":18.637,"vocabulary":9,"volume":53.844,"operands":{"distinct":4,"total":7.5},"operators":{"distinct":5,"total":7.75}},"params":0.75,"sloc":{"logical":3,"physical":10}},"module":"service/api-service.js","aggregate":{"complexity":{"cyclomatic":2,"cyclomaticDensity":13.333,"halstead":{"bugs":0.126,"difficulty":13,"effort":4894.746,"length":76,"time":271.93,"vocabulary":31,"volume":376.519,"operands":{"distinct":18,"total":36,"identifiers":["__stripped__"]},"operators":{"distinct":13,"total":40,"identifiers":["__stripped__"]}},"params":3,"sloc":{"logical":15,"physical":29}}},"functions":[{"cyclomatic":1,"cyclomaticDensity":20,"halstead":{"bugs":0.031,"difficulty":6.286,"effort":589.382,"length":24,"time":32.743,"vocabulary":15,"volume":93.765,"operands":{"distinct":7,"total":11,"identifiers":["__stripped__"]},"operators":{"distinct":8,"total":13,"identifiers":["__stripped__"]}},"params":1,"sloc":{"logical":5,"physical":19},"errors":[],"lineEnd":26,"lineStart":8,"name":"<anonymous>","complexity":{"cyclomatic":1,"sloc":{"logical":5,"physical":19},"halstead":{"bugs":0.031,"difficulty":6.286,"effort":589.382,"length":24,"time":32.743,"vocabulary":15,"volume":93.765,"operands":{"distinct":7,"total":11,"identifiers":["__stripped__"]},"operators":{"distinct":8,"total":13,"identifiers":["__stripped__"]}}},"line":8},{"cyclomatic":1,"cyclomaticDensity":100,"halstead":{"bugs":0.003,"difficulty":1.5,"effort":12,"length":4,"time":0.667,"vocabulary":4,"volume":8,"operands":{"distinct":1,"total":1,"identifiers":["__stripped__"]},"operators":{"distinct":3,"total":3,"identifiers":["__stripped__"]}},"params":0,"sloc":{"logical":1,"physical":9},"errors":[],"lineEnd":20,"lineStart":12,"name":"<anonymous>","complexity":{"cyclomatic":1,"sloc":{"logical":1,"physical":9},"halstead":{"bugs":0.003,"difficulty":1.5,"effort":12,"length":4,"time":0.667,"vocabulary":4,"volume":8,"operands":{"distinct":1,"total":1,"identifiers":["__stripped__"]},"operators":{"distinct":3,"total":3,"identifiers":["__stripped__"]}}},"line":12},{"cyclomatic":2,"cyclomaticDensity":50,"halstead":{"bugs":0.035,"difficulty":6.857,"effort":710.484,"length":28,"time":39.471,"vocabulary":13,"volume":103.612,"operands":{"distinct":7,"total":16,"identifiers":["__stripped__"]},"operators":{"distinct":6,"total":12,"identifiers":["__stripped__"]}},"params":2,"sloc":{"logical":4,"physical":7},"errors":[],"lineEnd":19,"lineStart":13,"name":"<anonymous>","complexity":{"cyclomatic":2,"sloc":{"logical":4,"physical":7},"halstead":{"bugs":0.035,"difficulty":6.857,"effort":710.484,"length":28,"time":39.471,"vocabulary":13,"volume":103.612,"operands":{"distinct":7,"total":16,"identifiers":["__stripped__"]},"operators":{"distinct":6,"total":12,"identifiers":["__stripped__"]}}},"line":13},{"cyclomatic":1,"cyclomaticDensity":50,"halstead":{"bugs":0.003,"difficulty":3,"effort":30,"length":5,"time":1.667,"vocabulary":4,"volume":10,"operands":{"distinct":1,"total":2,"identifiers":["__stripped__"]},"operators":{"distinct":3,"total":3,"identifiers":["__stripped__"]}},"params":0,"sloc":{"logical":2,"physical":5},"errors":[],"lineEnd":25,"lineStart":21,"name":"<anonymous>","complexity":{"cyclomatic":1,"sloc":{"logical":2,"physical":5},"halstead":{"bugs":0.003,"difficulty":3,"effort":30,"length":5,"time":1.667,"vocabulary":4,"volume":10,"operands":{"distinct":1,"total":2,"identifiers":["__stripped__"]},"operators":{"distinct":3,"total":3,"identifiers":["__stripped__"]}}},"line":21}]},"eslint":{"messages":[{"severity":"error","message":"Parsing error: sourceType 'module' is not supported when ecmaVersion < 2015. Consider adding `{ ecmaVersion: 2015 }` to the parser options.","fix":{}}]}}